[
    {
        "id": 248241715,
        "imageUrl": "https://cdn.dsmcdn.com//ty519/product/media/images/20220901/16/168205164/400027681/1/1_org_zoom.jpg",
        "brand": "SAUNA SUIT",
        "name": "Çene Altı Gıdı Eritme V Yüz Şekli Yanak Inceltme Kemeri Kayışı Güzellik Kemer",
        "category": "Yüz Masaj Aleti",
        "eventKey": "güzellik & bakım",
        "reviewsCount": 635,
        "soldCount": 787,
        "rating": 4.5,
        "price": 89.9
    },
    {
        "id": 766857631,
        "imageUrl": "https://cdn.dsmcdn.com//ty1006/product/media/images/prod/SPM/PIM/20231001/05/f95c2e16-1248-3f74-9773-5dc1365a494d/1_org_zoom.jpg",
        "brand": "Gerhau",
        "name": "Mooi Akıllı Güzellik Robotu V2- Yüz Kaldırma- - Ultrasonik Cilt Temizliği- Ems",
        "category": "Yüz Masaj Aleti",
        "eventKey": "güzellik & bakım",
        "reviewsCount": 4,
        "soldCount": 18,
        "rating": 5,
        "price": 2899
    },
    {
        "id": 39722673,
        "imageUrl": "https://cdn.dsmcdn.com//ty504/product/media/images/20220811/17/157966861/70332374/1/1_org_zoom.jpg",
        "brand": "3D",
        "name": "Güzellik Aleti Masaj Aleti Boyun Vücut Ayak Yüz Boyun  Aleti Platin Silindir",
        "category": "Yüz Masaj Aleti",
        "eventKey": "güzellik & bakım",
        "reviewsCount": 1008,
        "soldCount": 1331,
        "rating": 4.3,
        "price": 189
    },
    {
        "id": 788645923,
        "imageUrl": "https://cdn.dsmcdn.com//ty1112/product/media/images/prod/SPM/PIM/20231228/21/1b9d5a96-bd02-3f2b-8522-f212d4839d78/1_org_zoom.jpg",
        "brand": "NumuneMarket",
        "name": "Suhvee Ice Face Roller: Cilt Bakımınızın Yeni Sırrı Güzellikte Soğuk Masaj Face Rolleryüzsoğukterapi",
        "category": "Yüz Masaj Aleti",
        "eventKey": "güzellik & bakım",
        "reviewsCount": 4,
        "soldCount": 971,
        "rating": 5,
        "price": 239.9
    },
    {
        "id": 649704824,
        "imageUrl": "https://cdn.dsmcdn.com//ty733/product/media/images/20230215/21/281697905/858218681/1/1_org_zoom.jpg",
        "brand": "İLTERUS",
        "name": "3d Güzellik Platin Silindir Vücut Masaj Aleti",
        "category": "Yüz Masaj Aleti",
        "eventKey": "güzellik & bakım",
        "reviewsCount": 104,
        "soldCount": 427,
        "rating": 4.7,
        "price": 89.99
    },
    {
        "id": 422395247,
        "imageUrl": "https://cdn.dsmcdn.com//ty1008/product/media/images/prod/SPM/PIM/20231001/18/c1db3707-b50b-3449-a744-e12e6b8b6c3d/1_org_zoom.jpg",
        "brand": "Gerhau",
        "name": "Mooi Akıllı Güzellik Robotu V2 -yüz Kaldırma-kırışıklık Giderici-ultrasonik Cilt Temizliği-ems",
        "category": "Cilt Bakım Aletleri",
        "eventKey": "güzellik & bakım",
        "reviewsCount": 337,
        "soldCount": 1114,
        "rating": 4.6,
        "price": 2899
    },
    {
        "id": 376081591,
        "imageUrl": "https://cdn.dsmcdn.com//ty579/product/media/images/20221026/12/202694050/607527478/2/2_org_zoom.jpg",
        "brand": "Dove",
        "name": "Beauty Cream Bar Katı Güzellik Sabunu Original Nemledirici Etkili 90 G X8 + El Havlusu Hediye",
        "category": "Katı Sabun",
        "eventKey": "güzellik & bakım",
        "reviewsCount": 520,
        "soldCount": 1288,
        "rating": 4.8,
        "price": 230.9
    },
    {
        "id": 637873826,
        "imageUrl": "https://cdn.dsmcdn.com//ty734/product/media/images/20230215/21/281702799/842887505/1/1_org_zoom.jpg",
        "brand": "İLTERUS",
        "name": "Doğaltaş Yeşim Kalp Gua Sha Ve 3d Güzellik Platin Silindir Masaj Aleti",
        "category": "Yüz Masaj Aleti",
        "eventKey": "güzellik & bakım",
        "reviewsCount": 63,
        "soldCount": 181,
        "rating": 4.5,
        "price": 149.99
    },
    {
        "id": 336350986,
        "imageUrl": "https://cdn.dsmcdn.com//ty515/product/media/images/20220823/10/164228627/536351845/1/1_org_zoom.jpg",
        "brand": "Gülsha",
        "name": "Güzellik Misti",
        "category": "Tonik",
        "eventKey": "güzellik & bakım",
        "reviewsCount": 14,
        "soldCount": 861,
        "rating": 4.4,
        "price": 759
    },
    {
        "id": 778177869,
        "imageUrl": "https://cdn.dsmcdn.com//ty1034/product/media/images/prod/SPM/PIM/20231106/14/0e3f5e93-fafe-3da1-95cd-91e238e76107/1_org_zoom.jpg",
        "brand": "Mavessa",
        "name": "%100 Doğal At Kılı Selülit Vücut Fırçası-Yüz Fırçası- Masaj Aleti 3'lü Bakım Güzellik ve Terapi Seti",
        "category": "Selülit Fırçası",
        "eventKey": "güzellik & bakım",
        "reviewsCount": 1,
        "soldCount": 170,
        "rating": 5,
        "price": 399.9
    },
    {
        "id": 758445700,
        "imageUrl": "https://cdn.dsmcdn.com//ty995/product/media/images/prod/SPM/PIM/20230831/18/7076e1ed-b84f-3682-a7c6-d574146e464d/1_org_zoom.jpg",
        "brand": "DYPTEX",
        "name": "3 başlıklı boyun yüz göz gençleştirme, bakım ve güzellik cihazı Anti Aging yüz masaj",
        "category": "Yüz Masaj Aleti",
        "eventKey": "güzellik & bakım",
        "reviewsCount": 6,
        "soldCount": 454,
        "rating": 4.7,
        "price": 949
    },
    {
        "id": 725672154,
        "imageUrl": "https://cdn.dsmcdn.com//ty1014/product/media/images/prod/SPM/PIM/20231015/06/0a3622d7-e506-374b-b299-633f3ba15e64/1_org_zoom.jpg",
        "brand": "profozon",
        "name": "Kozmetik Guzellik Yara Yanık Sedef Egzama Mantar Uyuz Cilt Bakim Yaglari Ozon Kremi Formülü",
        "category": "Antibakteriyel Jel",
        "eventKey": "güzellik & bakım",
        "reviewsCount": 10,
        "soldCount": 839,
        "rating": 4.4,
        "price": 817
    },
    {
        "id": 788696790,
        "imageUrl": "https://cdn.dsmcdn.com//ty1111/product/media/images/prod/SPM/PIM/20231228/21/9cffb6a3-4fa8-3134-be27-db4c7ee3d241/1_org_zoom.jpg",
        "brand": "NumuneMarket",
        "name": "Suhvee Ice Face Roller: Cilt Bakımınızın Yeni Sırrı Güzellikte Soğuk Masaj Face Rolleryüzsoğukterapi",
        "category": "Yüz Masaj Aleti",
        "eventKey": "güzellik & bakım",
        "reviewsCount": 4,
        "soldCount": 923,
        "rating": 5,
        "price": 239.9
    },
    {
        "id": 42629774,
        "imageUrl": "https://cdn.dsmcdn.com//ty868/product/media/images/20230506/10/341677783/75740214/2/2_org_zoom.png",
        "brand": "Beauty Pillow",
        "name": "Kırışıklık Önleyici Ortopedik Güzellik Yastığı",
        "category": "Yastık",
        "eventKey": "güzellik & bakım",
        "reviewsCount": 1380,
        "soldCount": 1934,
        "rating": 4.2,
        "price": 1782.28
    },
    {
        "id": 787099610,
        "imageUrl": "https://cdn.dsmcdn.com//ty1080/product/media/images/prod/SPM/PIM/20231208/23/83f2cad1-0e01-3b32-924d-84d2d709417c/1_org_zoom.jpg",
        "brand": "MOJE MORE",
        "name": "Kırışıklık Karşıtı Güzellik Cihazı, Sıcak Kompres Işık Terapisi Ems Yüz Masajı Boyun Kaldırma",
        "category": "Yüz Masaj Aleti",
        "eventKey": "güzellik & bakım",
        "reviewsCount": 0,
        "soldCount": 802,
        "rating": null,
        "price": 1999
    },
    {
        "id": 252367631,
        "imageUrl": "https://cdn.dsmcdn.com//ty377/product/media/images/20220330/18/78998364/403661299/1/1_org_zoom.jpg",
        "brand": "Beauty Pillow",
        "name": "Kırışıklık Önleyici Ortopedik Güzellik Yastığı - Bej %100 Ipek Kılıf Ile",
        "category": "Yastık",
        "eventKey": "güzellik & bakım",
        "reviewsCount": 121,
        "soldCount": 571,
        "rating": 4.3,
        "price": 3399
    },
    {
        "id": 132744089,
        "imageUrl": "https://cdn.dsmcdn.com//ty947/product/media/images/20230607/23/383023490/227557733/1/1_org_zoom.jpg",
        "brand": "Mini Hifu",
        "name": "Hifu 2 Yüz Sıkılaştırma Germe Güzellik Cihazı Dermapen Yüz Ütüsü Cilt Kırışıklık Masaj Aleti",
        "category": "Yüz Masaj Aleti",
        "eventKey": "güzellik & bakım",
        "reviewsCount": 101,
        "soldCount": 749,
        "rating": 4.6,
        "price": 6999
    },
    {
        "id": 46557683,
        "imageUrl": "https://cdn.dsmcdn.com//ty1008/product/media/images/prod/SPM/PIM/20231003/10/5e23e8d9-9b65-395d-abd2-d33766f734ef/1_org_zoom.jpg",
        "brand": "Aclind",
        "name": "Yüz Kremi | Güzellik Serisi",
        "category": "Yüz Kremi",
        "eventKey": "güzellik & bakım",
        "reviewsCount": 3,
        "soldCount": 123,
        "rating": 3.7,
        "price": 79.99
    },
    {
        "id": 5897858,
        "imageUrl": "https://cdn.dsmcdn.com//ty106/product/media/images/20210421/17/81928633/19679160/1/1_org_zoom.jpg",
        "brand": "Nivea",
        "name": "Urban Skin Detox Güzellik Uykusu Maskesi 50 ml",
        "category": "Yüz Maskesi",
        "eventKey": "güzellik & bakım",
        "reviewsCount": 209,
        "soldCount": 658,
        "rating": 4.5,
        "price": 178.19
    },
    {
        "id": 679900474,
        "imageUrl": "https://cdn.dsmcdn.com//ty1121/product/media/images/prod/SPM/PIM/20240103/17/0688e55d-a173-393d-b549-852803719d06/1_org_zoom.jpg",
        "brand": "AGE PILLOW",
        "name": "Anti Age Kırışıklık Önleyici Güzellik Yastığı - Ortopedik Yüksek Boyun Destek Collagentech Patentli",
        "category": "Yastık",
        "eventKey": "güzellik & bakım",
        "reviewsCount": 29,
        "soldCount": 484,
        "rating": 4.6,
        "price": 1695
    },
    {
        "id": 769703839,
        "imageUrl": "https://cdn.dsmcdn.com//ty1013/product/media/images/prod/SPM/PIM/20231011/15/c9a81adc-80b6-3b07-8989-7f613090948b/1_org_zoom.jpg",
        "brand": "THE RUSH",
        "name": "Yüz ve Göz Çift Başlık Kaldırma Sıkılaştırıcı Yüz Spa Güzellik Masaj Cihazı",
        "category": "Yüz Masaj Aleti",
        "eventKey": "güzellik & bakım",
        "reviewsCount": 2,
        "soldCount": 650,
        "rating": 4.5,
        "price": 199
    },
    {
        "id": 87286468,
        "imageUrl": "https://cdn.dsmcdn.com//ty992/product/media/images/prod/SPM/PIM/20230824/09/050dc298-7420-3bb2-9ec8-0fa87e5bdf26/1_org_zoom.jpg",
        "brand": "Aclind",
        "name": "® Dual Actıve Make-up Remover 125 ml | Çift Fazlı Cilt Makyaj Temizleyici | Güzellik Serisi",
        "category": "Göz Makyaj Temizleyici",
        "eventKey": "güzellik & bakım",
        "reviewsCount": 0,
        "soldCount": 863,
        "rating": null,
        "price": 85.07
    },
    {
        "id": 637879793,
        "imageUrl": "https://cdn.dsmcdn.com//ty737/product/media/images/20230217/17/282770812/842897622/1/1_org_zoom.jpg",
        "brand": "İLTERUS",
        "name": "Doğaltaş Yeşim Face Roller Ve 3d Güzellik Platin Silindir Masaj Aleti",
        "category": "Yüz Masaj Aleti",
        "eventKey": "güzellik & bakım",
        "reviewsCount": 0,
        "soldCount": 291,
        "rating": null,
        "price": 149.99
    },
    {
        "id": 73208825,
        "imageUrl": "https://cdn.dsmcdn.com//ty45/product/media/images/20210104/11/45638479/126136454/1/1_org_zoom.jpg",
        "brand": "Unikum",
        "name": "Jade Roller Yüz Masaj Aleti Cilt Yenileme Doğal Yeşim Taşı Cihazı Cilt Bakımı Ve Güzellik",
        "category": "Yüz Masaj Aleti",
        "eventKey": "güzellik & bakım",
        "reviewsCount": 0,
        "soldCount": 19,
        "rating": null,
        "price": 89
    },
    {
        "id": 735392323,
        "imageUrl": "https://cdn.dsmcdn.com//ty970/product/media/images/20230723/20/396175243/966997725/1/1_org_zoom.jpg",
        "brand": "hifu",
        "name": "Premium Yüz Sıkılaştırma Gerdirme Cihazı Cilt Gençleştirme Anti Aging Yüz Ütüsü Güzellik Aleti",
        "category": "Yüz Masaj Aleti",
        "eventKey": "güzellik & bakım",
        "reviewsCount": 5,
        "soldCount": 738,
        "rating": 5,
        "price": 14999
    },
    {
        "id": 766857631,
        "imageUrl": "https://cdn.dsmcdn.com//ty1006/product/media/images/prod/SPM/PIM/20231001/05/f95c2e16-1248-3f74-9773-5dc1365a494d/1_org_zoom.jpg",
        "brand": "Gerhau",
        "name": "Mooi Akıllı Güzellik Robotu V2- Yüz Kaldırma- - Ultrasonik Cilt Temizliği- Ems",
        "category": "Yüz Masaj Aleti",
        "eventKey": "güzellik & bakım",
        "reviewsCount": 4,
        "soldCount": 1001,
        "rating": 5,
        "price": 2899
    },
    {
        "id": 708703157,
        "imageUrl": "https://cdn.dsmcdn.com//ty879/product/media/images/20230512/16/347271485/935952215/1/1_org_zoom.jpg",
        "brand": "gattstone",
        "name": "Doğal Ametist Taşı Gua Sha Yüz Masaj Aleti - Doğanın Dokunuşuyla Güzelliği Keşfedin-%100 Orijinal",
        "category": "Yüz Masaj Aleti",
        "eventKey": "güzellik & bakım",
        "reviewsCount": 0,
        "soldCount": 725,
        "rating": null,
        "price": 150
    },
    {
        "id": 788645923,
        "imageUrl": "https://cdn.dsmcdn.com//ty1112/product/media/images/prod/SPM/PIM/20231228/21/1b9d5a96-bd02-3f2b-8522-f212d4839d78/1_org_zoom.jpg",
        "brand": "NumuneMarket",
        "name": "Suhvee Ice Face Roller: Cilt Bakımınızın Yeni Sırrı Güzellikte Soğuk Masaj Face Rolleryüzsoğukterapi",
        "category": "Yüz Masaj Aleti",
        "eventKey": "güzellik & bakım",
        "reviewsCount": 4,
        "soldCount": 654,
        "rating": 5,
        "price": 239.9
    },
    {
        "id": 104956704,
        "imageUrl": "https://cdn.dsmcdn.com//ty513/product/media/images/20220823/19/164551728/173268510/1/1_org_zoom.jpg",
        "brand": "TheBeautyStore",
        "name": "Yüz Gıdı Boyun Ense Gerdirme Şekillendirme Güzellik Cihazı Cilt Gençleştirme Sıkılaştırma Makinesi",
        "category": "Yüz Masaj Aleti",
        "eventKey": "güzellik & bakım",
        "reviewsCount": 0,
        "soldCount": 889,
        "rating": null,
        "price": 5999
    },
    {
        "id": 422395247,
        "imageUrl": "https://cdn.dsmcdn.com//ty1008/product/media/images/prod/SPM/PIM/20231001/18/c1db3707-b50b-3449-a744-e12e6b8b6c3d/1_org_zoom.jpg",
        "brand": "Gerhau",
        "name": "Mooi Akıllı Güzellik Robotu V2 -yüz Kaldırma-kırışıklık Giderici-ultrasonik Cilt Temizliği-ems",
        "category": "Cilt Bakım Aletleri",
        "eventKey": "güzellik & bakım",
        "reviewsCount": 337,
        "soldCount": 958,
        "rating": 4.6,
        "price": 2899
    },
    {
        "id": 754224140,
        "imageUrl": "https://cdn.dsmcdn.com//ty988/product/media/images/prod/SPM/PIM/20230822/16/182e8268-f98b-39ed-88c0-30c412b4f043/1_org_zoom.jpg",
        "brand": "Jewval",
        "name": "V Yüz Konturu için Akıllı Güzellik ve Yüz İnceltme Cihazı Yüz Germe Gıdı Yanak Toparlama",
        "category": "Yüz Masaj Aleti",
        "eventKey": "güzellik & bakım",
        "reviewsCount": 1,
        "soldCount": 173,
        "rating": 5,
        "price": 5945.53
    },
    {
        "id": 376081591,
        "imageUrl": "https://cdn.dsmcdn.com//ty579/product/media/images/20221026/12/202694050/607527478/2/2_org_zoom.jpg",
        "brand": "Dove",
        "name": "Beauty Cream Bar Katı Güzellik Sabunu Original Nemledirici Etkili 90 G X8 + El Havlusu Hediye",
        "category": "Katı Sabun",
        "eventKey": "güzellik & bakım",
        "reviewsCount": 520,
        "soldCount": 768,
        "rating": 4.8,
        "price": 230.9
    },
    {
        "id": 469706012,
        "imageUrl": "https://cdn.dsmcdn.com//ty963/product/media/images/20230713/18/393580923/669439161/1/1_org_zoom.jpg",
        "brand": "TheBeautyStore",
        "name": "Mikro Akım Yüz Lifting Germe Sıkılaştırma Cihazı Cilt Güzellik Anti Aging Masaj Aleti",
        "category": "Yüz Masaj Aleti",
        "eventKey": "güzellik & bakım",
        "reviewsCount": 0,
        "soldCount": 191,
        "rating": null,
        "price": 9999
    },
    {
        "id": 336350986,
        "imageUrl": "https://cdn.dsmcdn.com//ty515/product/media/images/20220823/10/164228627/536351845/1/1_org_zoom.jpg",
        "brand": "Gülsha",
        "name": "Güzellik Misti",
        "category": "Tonik",
        "eventKey": "güzellik & bakım",
        "reviewsCount": 14,
        "soldCount": 498,
        "rating": 4.4,
        "price": 759
    },
    {
        "id": 761360772,
        "imageUrl": "https://cdn.dsmcdn.com//ty999/product/media/images/prod/SPM/PIM/20230914/16/eeaade0c-fe50-3e65-9c98-839f7c32d62d/1_org_zoom.jpg",
        "brand": "Utelips",
        "name": "Elektrikli Mikro Akım Yüz Masajı Sıkılaştırma Kırışıklık Karşıtı Cilt Gençleştirme Güzellik Aleti",
        "category": "Yüz Masaj Aleti",
        "eventKey": "güzellik & bakım",
        "reviewsCount": 4,
        "soldCount": 734,
        "rating": 1,
        "price": 1299.9
    },
    {
        "id": 778177869,
        "imageUrl": "https://cdn.dsmcdn.com//ty1034/product/media/images/prod/SPM/PIM/20231106/14/0e3f5e93-fafe-3da1-95cd-91e238e76107/1_org_zoom.jpg",
        "brand": "Mavessa",
        "name": "%100 Doğal At Kılı Selülit Vücut Fırçası-Yüz Fırçası- Masaj Aleti 3'lü Bakım Güzellik ve Terapi Seti",
        "category": "Selülit Fırçası",
        "eventKey": "güzellik & bakım",
        "reviewsCount": 1,
        "soldCount": 17,
        "rating": 5,
        "price": 399.9
    },
    {
        "id": 58322959,
        "imageUrl": "https://cdn.dsmcdn.com//ty22/product/media/images/20201109/14/24391829/103219612/1/1_org_zoom.jpg",
        "brand": "Farmasi",
        "name": "Age Reversist All Nıght Beauty Gece Güzellik Maskesi 50 Ml",
        "category": "Yüz Maskesi",
        "eventKey": "güzellik & bakım",
        "reviewsCount": 58,
        "soldCount": 175,
        "rating": 4.7,
        "price": 239.99
    },
    {
        "id": 725672154,
        "imageUrl": "https://cdn.dsmcdn.com//ty1014/product/media/images/prod/SPM/PIM/20231015/06/0a3622d7-e506-374b-b299-633f3ba15e64/1_org_zoom.jpg",
        "brand": "profozon",
        "name": "Kozmetik Guzellik Yara Yanık Sedef Egzama Mantar Uyuz Cilt Bakim Yaglari Ozon Kremi Formülü",
        "category": "Antibakteriyel Jel",
        "eventKey": "güzellik & bakım",
        "reviewsCount": 10,
        "soldCount": 192,
        "rating": 4.4,
        "price": 817
    },
    {
        "id": 675649084,
        "imageUrl": "https://cdn.dsmcdn.com//ty793/product/media/images/20230323/16/310374178/893892838/1/1_org_zoom.jpg",
        "brand": "hello foam cat",
        "name": "Yüz Kırışıklarına Karşı 16 Parca Yapışkan Maske Tekrar Tekrar Güzellik Yüz Alın Boyun Göz Için",
        "category": "Yüz Maskesi",
        "eventKey": "güzellik & bakım",
        "reviewsCount": 0,
        "soldCount": 235,
        "rating": null,
        "price": 741
    },
    {
        "id": 42629774,
        "imageUrl": "https://cdn.dsmcdn.com//ty868/product/media/images/20230506/10/341677783/75740214/2/2_org_zoom.png",
        "brand": "Beauty Pillow",
        "name": "Kırışıklık Önleyici Ortopedik Güzellik Yastığı",
        "category": "Yastık",
        "eventKey": "güzellik & bakım",
        "reviewsCount": 1380,
        "soldCount": 2115,
        "rating": 4.2,
        "price": 1782.28
    },
    {
        "id": 243543946,
        "imageUrl": "https://cdn.dsmcdn.com//ty784/product/media/images/20230317/9/305846623/390945221/1/1_org_zoom.jpg",
        "brand": "Aurelia Genève",
        "name": "-t- Shaped Energy Beauty Bar - Karşıtı & Çizgi Giderici Titreşimli -t- Güzellik Masaj Aleti",
        "category": "Yüz Masaj Aleti",
        "eventKey": "güzellik & bakım",
        "reviewsCount": 9,
        "soldCount": 177,
        "rating": 5,
        "price": 1320
    },
    {
        "id": 252367631,
        "imageUrl": "https://cdn.dsmcdn.com//ty377/product/media/images/20220330/18/78998364/403661299/1/1_org_zoom.jpg",
        "brand": "Beauty Pillow",
        "name": "Kırışıklık Önleyici Ortopedik Güzellik Yastığı - Bej %100 Ipek Kılıf Ile",
        "category": "Yastık",
        "eventKey": "güzellik & bakım",
        "reviewsCount": 121,
        "soldCount": 522,
        "rating": 4.3,
        "price": 3399
    },
    {
        "id": 156352750,
        "imageUrl": "https://cdn.dsmcdn.com//ty335/product/media/images/20220219/0/53318200/258490357/1/1_org_zoom.jpg",
        "brand": "schwartz",
        "name": "Titreşimli Yüz Masajı Güzellik Bakımı T Şekli",
        "category": "Yüz Masaj Aleti",
        "eventKey": "güzellik & bakım",
        "reviewsCount": 126,
        "soldCount": 225,
        "rating": 4.0,
        "price": 285
    },
    {
        "id": 46557683,
        "imageUrl": "https://cdn.dsmcdn.com//ty1008/product/media/images/prod/SPM/PIM/20231003/10/5e23e8d9-9b65-395d-abd2-d33766f734ef/1_org_zoom.jpg",
        "brand": "Aclind",
        "name": "Yüz Kremi | Güzellik Serisi",
        "category": "Yüz Kremi",
        "eventKey": "güzellik & bakım",
        "reviewsCount": 3,
        "soldCount": 402,
        "rating": 3.7,
        "price": 79.99
    },
    {
        "id": 87263508,
        "imageUrl": "https://cdn.dsmcdn.com//ty75/product/media/images/20210225/12/66845150/145980799/1/1_org_zoom.jpg",
        "brand": "ELİGE",
        "name": "Inci Tozu Organik %100 Saf - Maske-bakım-güzellik",
        "category": "Yüz Maskesi",
        "eventKey": "güzellik & bakım",
        "reviewsCount": 10,
        "soldCount": 478,
        "rating": 4.2,
        "price": 159
    },
    {
        "id": 679900474,
        "imageUrl": "https://cdn.dsmcdn.com//ty1121/product/media/images/prod/SPM/PIM/20240103/17/0688e55d-a173-393d-b549-852803719d06/1_org_zoom.jpg",
        "brand": "AGE PILLOW",
        "name": "Anti Age Kırışıklık Önleyici Güzellik Yastığı - Ortopedik Yüksek Boyun Destek Collagentech Patentli",
        "category": "Yastık",
        "eventKey": "güzellik & bakım",
        "reviewsCount": 29,
        "soldCount": 535,
        "rating": 4.6,
        "price": 1695
    },
    {
        "id": 699348134,
        "imageUrl": "https://cdn.dsmcdn.com//ty859/product/media/images/20230503/0/337672559/924602480/1/1_org_zoom.jpg",
        "brand": "Havana",
        "name": "Dermapen Cihazı Yüz Mezoterapi Sıkılaştırma Germe Iz Leke Giderme Cilt Güzellik Aleti Led",
        "category": "Yüz Masaj Aleti",
        "eventKey": "güzellik & bakım",
        "reviewsCount": 1,
        "soldCount": 478,
        "rating": 5,
        "price": 550
    },
    {
        "id": 87286468,
        "imageUrl": "https://cdn.dsmcdn.com//ty992/product/media/images/prod/SPM/PIM/20230824/09/050dc298-7420-3bb2-9ec8-0fa87e5bdf26/1_org_zoom.jpg",
        "brand": "Aclind",
        "name": "® Dual Actıve Make-up Remover 125 ml | Çift Fazlı Cilt Makyaj Temizleyici | Güzellik Serisi",
        "category": "Göz Makyaj Temizleyici",
        "eventKey": "güzellik & bakım",
        "reviewsCount": 0,
        "soldCount": 193,
        "rating": null,
        "price": 85.07
    },
    {
        "id": 81997214,
        "imageUrl": "https://cdn.dsmcdn.com//ty118/product/media/images/20210524/17/91187181/138593696/1/1_org_zoom.jpg",
        "brand": "Nivea",
        "name": "Aqua Sensatıon Canlandırıcı Bakım Kremi 50 Ml & Detox Güzellik Uykusu Maskesi - Urban Skin 50 Ml",
        "category": "Yüz Maskesi",
        "eventKey": "güzellik & bakım",
        "reviewsCount": 9,
        "soldCount": 217,
        "rating": 4.7,
        "price": 399.9
    },
    {
        "id": 766857631,
        "imageUrl": "https://cdn.dsmcdn.com//ty1006/product/media/images/prod/SPM/PIM/20231001/05/f95c2e16-1248-3f74-9773-5dc1365a494d/1_org_zoom.jpg",
        "brand": "Gerhau",
        "name": "Mooi Akıllı Güzellik Robotu V2- Yüz Kaldırma- - Ultrasonik Cilt Temizliği- Ems",
        "category": "Yüz Masaj Aleti",
        "eventKey": "güzellik & bakım",
        "reviewsCount": 4,
        "soldCount": 867,
        "rating": 5,
        "price": 2899
    },
    {
        "id": 52597648,
        "imageUrl": "https://cdn.dsmcdn.com//ty2/product/media/images/20201015/11/15901569/93506924/1/1_org_zoom.jpg",
        "brand": "Nivea",
        "name": "Detox Güzellik Uykusu Maskesi - Urban Skin 50 ml 1100010002619",
        "category": "Yüz Maskesi",
        "eventKey": "güzellik & bakım",
        "reviewsCount": 0,
        "soldCount": 420,
        "rating": null,
        "price": 279.9
    },
    {
        "id": 788645923,
        "imageUrl": "https://cdn.dsmcdn.com//ty1112/product/media/images/prod/SPM/PIM/20231228/21/1b9d5a96-bd02-3f2b-8522-f212d4839d78/1_org_zoom.jpg",
        "brand": "NumuneMarket",
        "name": "Suhvee Ice Face Roller: Cilt Bakımınızın Yeni Sırrı Güzellikte Soğuk Masaj Face Rolleryüzsoğukterapi",
        "category": "Yüz Masaj Aleti",
        "eventKey": "güzellik & bakım",
        "reviewsCount": 4,
        "soldCount": 629,
        "rating": 5,
        "price": 239.9
    },
    {
        "id": 761188857,
        "imageUrl": "https://cdn.dsmcdn.com//ty1001/product/media/images/prod/SPM/PIM/20230912/20/28d16ccb-ad0c-3d19-abad-6a029adb2ada/1_org_zoom.jpg",
        "brand": "TECHNOFAST",
        "name": "Güzellik Aleti Masaj Aleti Boyun Vücut Ayak Yüz Boyun Aleti Platin Silindir",
        "category": "Yüz Masaj Aleti",
        "eventKey": "güzellik & bakım",
        "reviewsCount": 0,
        "soldCount": 439,
        "rating": null,
        "price": 99.9
    },
    {
        "id": 422395247,
        "imageUrl": "https://cdn.dsmcdn.com//ty1008/product/media/images/prod/SPM/PIM/20231001/18/c1db3707-b50b-3449-a744-e12e6b8b6c3d/1_org_zoom.jpg",
        "brand": "Gerhau",
        "name": "Mooi Akıllı Güzellik Robotu V2 -yüz Kaldırma-kırışıklık Giderici-ultrasonik Cilt Temizliği-ems",
        "category": "Cilt Bakım Aletleri",
        "eventKey": "güzellik & bakım",
        "reviewsCount": 337,
        "soldCount": 1185,
        "rating": 4.6,
        "price": 2899
    },
    {
        "id": 381921353,
        "imageUrl": "https://cdn.dsmcdn.com//ty593/product/media/images/20221108/9/209857716/616863934/1/1_org_zoom.jpg",
        "brand": "Utelips",
        "name": "V-yüz Yüz Kaldırma Kadın Güzellik Çene Yapışma Anti Kırışıklık Asılı Kulaklar Kaldırma Maskesi Germe",
        "category": "Yüz Maskesi",
        "eventKey": "güzellik & bakım",
        "reviewsCount": 1,
        "soldCount": 729,
        "rating": 5,
        "price": 124.9
    },
    {
        "id": 376081591,
        "imageUrl": "https://cdn.dsmcdn.com//ty579/product/media/images/20221026/12/202694050/607527478/2/2_org_zoom.jpg",
        "brand": "Dove",
        "name": "Beauty Cream Bar Katı Güzellik Sabunu Original Nemledirici Etkili 90 G X8 + El Havlusu Hediye",
        "category": "Katı Sabun",
        "eventKey": "güzellik & bakım",
        "reviewsCount": 520,
        "soldCount": 1382,
        "rating": 4.8,
        "price": 230.9
    },
    {
        "id": 765477302,
        "imageUrl": "https://cdn.dsmcdn.com//ty1005/product/media/images/prod/SPM/PIM/20230927/22/27c84cbc-8694-3860-ab61-d7d03a4b6c0c/1_org_zoom.jpg",
        "brand": "Planet Essence",
        "name": "Fenomen C Yüz Maskesi 60ml--Saklı Guzellik--",
        "category": "Yüz Maskesi",
        "eventKey": "güzellik & bakım",
        "reviewsCount": 0,
        "soldCount": 718,
        "rating": null,
        "price": 398
    },
    {
        "id": 336350986,
        "imageUrl": "https://cdn.dsmcdn.com//ty515/product/media/images/20220823/10/164228627/536351845/1/1_org_zoom.jpg",
        "brand": "Gülsha",
        "name": "Güzellik Misti",
        "category": "Tonik",
        "eventKey": "güzellik & bakım",
        "reviewsCount": 14,
        "soldCount": 999,
        "rating": 4.4,
        "price": 759
    },
    {
        "id": 785483237,
        "imageUrl": "https://cdn.dsmcdn.com//ty1075/product/media/images/prod/SPM/PIM/20231203/01/bdf033e2-bdf9-3b90-bcd1-3dddcb1869ab/1_org_zoom.jpg",
        "brand": "Utelips",
        "name": "Buz Rulo Kalıp Yüz Göz Cilt Bakımı Buz Yüz Silikon Küp Masaj Ev Güzellik Aleti Pro Ice Face Roller",
        "category": "Yüz Masaj Aleti",
        "eventKey": "güzellik & bakım",
        "reviewsCount": 0,
        "soldCount": 456,
        "rating": null,
        "price": 729.9
    },
    {
        "id": 778177869,
        "imageUrl": "https://cdn.dsmcdn.com//ty1034/product/media/images/prod/SPM/PIM/20231106/14/0e3f5e93-fafe-3da1-95cd-91e238e76107/1_org_zoom.jpg",
        "brand": "Mavessa",
        "name": "%100 Doğal At Kılı Selülit Vücut Fırçası-Yüz Fırçası- Masaj Aleti 3'lü Bakım Güzellik ve Terapi Seti",
        "category": "Selülit Fırçası",
        "eventKey": "güzellik & bakım",
        "reviewsCount": 1,
        "soldCount": 464,
        "rating": 5,
        "price": 399.9
    },
    {
        "id": 773472972,
        "imageUrl": "https://cdn.dsmcdn.com//ty1020/product/media/images/prod/SPM/PIM/20231022/22/10b7bdc4-07a3-3a9f-b8fe-92763ed92c19/1_org_zoom.jpg",
        "brand": "MSW",
        "name": "Yüz Masajı, Cilt Bakımı Güzellik Cihazı için 45 ° Termal Yüz Masajı",
        "category": "Yüz Masaj Aleti",
        "eventKey": "güzellik & bakım",
        "reviewsCount": 0,
        "soldCount": 715,
        "rating": null,
        "price": 7699
    },
    {
        "id": 725672154,
        "imageUrl": "https://cdn.dsmcdn.com//ty1014/product/media/images/prod/SPM/PIM/20231015/06/0a3622d7-e506-374b-b299-633f3ba15e64/1_org_zoom.jpg",
        "brand": "profozon",
        "name": "Kozmetik Guzellik Yara Yanık Sedef Egzama Mantar Uyuz Cilt Bakim Yaglari Ozon Kremi Formülü",
        "category": "Antibakteriyel Jel",
        "eventKey": "güzellik & bakım",
        "reviewsCount": 10,
        "soldCount": 861,
        "rating": 4.4,
        "price": 817
    },
    {
        "id": 782987623,
        "imageUrl": "https://cdn.dsmcdn.com//ty1059/product/media/images/prod/SPM/PIM/20231123/20/69cd2269-c86a-36e9-a295-fb53970028d3/1_org_zoom.jpg",
        "brand": "Shiseido",
        "name": "C Vitamini İçerikli Nemlendirici Gece Güzellik Maskesi 50 ml",
        "category": "Yüz Maskesi",
        "eventKey": "güzellik & bakım",
        "reviewsCount": 0,
        "soldCount": 134,
        "rating": null,
        "price": 3562.5
    },
    {
        "id": 42629774,
        "imageUrl": "https://cdn.dsmcdn.com//ty868/product/media/images/20230506/10/341677783/75740214/2/2_org_zoom.png",
        "brand": "Beauty Pillow",
        "name": "Kırışıklık Önleyici Ortopedik Güzellik Yastığı",
        "category": "Yastık",
        "eventKey": "güzellik & bakım",
        "reviewsCount": 1380,
        "soldCount": 1455,
        "rating": 4.2,
        "price": 1782.28
    },
    {
        "id": 736136715,
        "imageUrl": "https://cdn.dsmcdn.com//ty962/product/media/images/20230706/17/391680280/968055551/1/1_org_zoom.jpg",
        "brand": "Dr.Well BARCELONA Estetik & Güzellik",
        "name": "Siyah Nokta & Akne Karşıtı, Gözenek Sıkılaştırıcı, Arındırıcı Kil Maskesi 200ml",
        "category": "Yüz Maskesi",
        "eventKey": "güzellik & bakım",
        "reviewsCount": 0,
        "soldCount": 218,
        "rating": null,
        "price": 649
    },
    {
        "id": 252367631,
        "imageUrl": "https://cdn.dsmcdn.com//ty377/product/media/images/20220330/18/78998364/403661299/1/1_org_zoom.jpg",
        "brand": "Beauty Pillow",
        "name": "Kırışıklık Önleyici Ortopedik Güzellik Yastığı - Bej %100 Ipek Kılıf Ile",
        "category": "Yastık",
        "eventKey": "güzellik & bakım",
        "reviewsCount": 121,
        "soldCount": 1004,
        "rating": 4.3,
        "price": 3399
    },
    {
        "id": 282786219,
        "imageUrl": "https://cdn.dsmcdn.com//ty1049/product/media/images/prod/SPM/PIM/20231116/14/004ddc36-d81f-3b88-b0d4-c2b32713beb3/1_org_zoom.jpg",
        "brand": "Galancy",
        "name": "Gözenek Temizleyici, Kolajen, Hyaluronic Acid, Sıkılışatırıcı Ve Güzellik Maskesi 200gr",
        "category": "Yüz Maskesi",
        "eventKey": "güzellik & bakım",
        "reviewsCount": 20,
        "soldCount": 1008,
        "rating": 4.0,
        "price": 150
    },
    {
        "id": 46557683,
        "imageUrl": "https://cdn.dsmcdn.com//ty1008/product/media/images/prod/SPM/PIM/20231003/10/5e23e8d9-9b65-395d-abd2-d33766f734ef/1_org_zoom.jpg",
        "brand": "Aclind",
        "name": "Yüz Kremi | Güzellik Serisi",
        "category": "Yüz Kremi",
        "eventKey": "güzellik & bakım",
        "reviewsCount": 3,
        "soldCount": 26,
        "rating": 3.7,
        "price": 79.99
    },
    {
        "id": 792019279,
        "imageUrl": "https://cdn.dsmcdn.com//ty1109/product/media/images/prod/SPM/PIM/20231225/18/dd288253-e123-322d-ad44-04228f57b91b/1_org_zoom.jpg",
        "brand": "Touchbeauty",
        "name": "3'ü 1 Arada Güzellik Cihazı, Yaşlanma Karşıtı için Çok Fonksiyonlu,Yüz Germe",
        "category": "Yüz Masaj Aleti",
        "eventKey": "güzellik & bakım",
        "reviewsCount": 0,
        "soldCount": 430,
        "rating": null,
        "price": 11599
    },
    {
        "id": 679900474,
        "imageUrl": "https://cdn.dsmcdn.com//ty1121/product/media/images/prod/SPM/PIM/20240103/17/0688e55d-a173-393d-b549-852803719d06/1_org_zoom.jpg",
        "brand": "AGE PILLOW",
        "name": "Anti Age Kırışıklık Önleyici Güzellik Yastığı - Ortopedik Yüksek Boyun Destek Collagentech Patentli",
        "category": "Yastık",
        "eventKey": "güzellik & bakım",
        "reviewsCount": 29,
        "soldCount": 379,
        "rating": 4.6,
        "price": 1695
    },
    {
        "id": 506611983,
        "imageUrl": "https://cdn.dsmcdn.com//ty695/product/media/images/20230120/9/262087731/708806733/1/1_org_zoom.jpg",
        "brand": "TechnoStation",
        "name": "Güzellik Aleti Masaj Aleti Boyun Vücut Ayak Yüz Boyun Aleti Platin Silindir",
        "category": "Yüz Masaj Aleti",
        "eventKey": "güzellik & bakım",
        "reviewsCount": 0,
        "soldCount": 924,
        "rating": null,
        "price": 99.9
    },
    {
        "id": 87286468,
        "imageUrl": "https://cdn.dsmcdn.com//ty992/product/media/images/prod/SPM/PIM/20230824/09/050dc298-7420-3bb2-9ec8-0fa87e5bdf26/1_org_zoom.jpg",
        "brand": "Aclind",
        "name": "® Dual Actıve Make-up Remover 125 ml | Çift Fazlı Cilt Makyaj Temizleyici | Güzellik Serisi",
        "category": "Göz Makyaj Temizleyici",
        "eventKey": "güzellik & bakım",
        "reviewsCount": 0,
        "soldCount": 875,
        "rating": null,
        "price": 85.07
    }
]